<alpino_ds version="1.14">
  <node begin="0" cat="top" end="8" id="0" rel="top">
    <node begin="0" cat="du" end="7" id="1" rel="--">
      <node begin="0" conjtype="neven" end="1" id="2" lemma="en" pos="comp" postag="VG(neven)" pt="vg" rel="dlink" root="en" sense="en" word="en"/>
      <node begin="1" cat="smain" end="7" id="3" rel="nucl">
        <node begin="2" end="3" id="4" lemma="hebben" pos="verb" postag="WW(pv,tgw,ev)" pt="ww" pvagr="ev" pvtijd="tgw" rel="hd" root="heb" sense="heb" word="heb" wvorm="pv"/>
        <node begin="3" end="4" getal="ev" id="5" index="1" lemma="ik" naamval="nomin" pdtype="pron" persoon="1" pos="pron" postag="VNW(pers,pron,nomin,vol,1,ev)" pt="vnw" rel="su" root="ik" sense="ik" status="vol" vwtype="pers" word="ik"/>
        <node begin="1" cat="ppart" end="7" id="6" rel="vc">
          <node begin="1" end="2" id="7" lemma="dan" pos="adv" postag="BW()" pt="bw" rel="mod" root="dan" sense="dan" word="dan"/>
          <node begin="3" end="4" id="8" index="1" rel="su"/>
          <node begin="4" end="5" genus="masc" getal="ev" id="9" lemma="hem" naamval="obl" pdtype="pron" persoon="3" pos="pron" postag="VNW(pers,pron,obl,vol,3,ev,masc)" pt="vnw" rel="obj1" root="hem" sense="hem" status="vol" vwtype="pers" word="hem"/>
          <node begin="5" end="6" id="10" lemma="binnen" pos="adv" postag="VZ(fin)" pt="vz" rel="svp" root="binnen" sense="binnen" vztype="fin" word="binnen"/>
          <node begin="6" buiging="zonder" end="7" id="11" lemma="binnen_trekken" pos="verb" positie="vrij" postag="WW(vd,vrij,zonder)" pt="ww" rel="hd" root="trek_binnen" sense="trek_binnen" word="getrokken" wvorm="vd"/>
        </node>
      </node>
    </node>
    <node begin="7" end="8" id="12" lemma="." pos="punct" postag="LET()" pt="let" rel="--" root="." sense="." word="."/>
  </node>
  <sentence sentid="H016p_3--H016p_3_1--0276c">en dan heb ik hem binnen getrokken .</sentence>
  <comments>
    <comment>Q#H016p_3--H016p_3_1--0276c|en dan heb ik hem binnen getrokken .|1|1|-5.0976826083999995</comment>
  </comments>
</alpino_ds>