[
{
    "sourcePath": "source-data/clariah-evaluation-15",
    "trainingPath": "training-data/clariah-evaluation-15",
    "columns": [
        "token",
        "pos",
        "lemma"
    ],
    "name": "clariah-evaluation-15",
    "eraFrom": "1400",
    "eraTo": "1500",
    "tagset": "TDN-Core",
    "dataset": true,
    "public": true,
    "sourceName": "clariah-evaluation-15",
    "sourceURL": "https://dbnl.org",
    "version": "0.9",
    "description": "CLARIAH Evaluation set 1400-1500"
},
{
    "sourcePath": "source-data/clariah-evaluation-16",
    "trainingPath": "training-data/clariah-evaluation-16",
    "columns": [
        "token",
        "pos",
        "lemma"
    ],
    "name": "clariah-evaluation-16",
    "eraFrom": "1500",
    "eraTo": "1600",
    "tagset": "TDN-Core",
    "dataset": true,
    "public": true,
    "sourceName": "clariah-evaluation-16",
    "sourceURL": "https://dbnl.org",
    "version": "0.9",
    "description": "CLARIAH Evaluation Set 1500-1600 "
},
{
    "sourcePath": "source-data/clariah-evaluation-17",
    "trainingPath": "training-data/clariah-evaluation-17",
    "columns": [
        "token",
        "pos",
        "lemma"
    ],
    "name": "clariah-evaluation-17",
    "eraFrom": "1600",
    "eraTo": "1700",
    "tagset": "TDN-Core",
    "dataset": true,
    "public": true,
    "sourceName": "clariah-evaluation-17",
    "sourceURL": "https://dbnl.org",
    "version": "0.9",
    "description": "CLARIAH Evaluation Set 1600-1700"
},
{
    "sourcePath": "source-data/clariah-evaluation-18",
    "trainingPath": "training-data/clariah-evaluation-18",
    "columns": [
        "token",
        "pos",
        "lemma"
    ],
    "name": "clariah-evaluation-18",
    "eraFrom": "1700",
    "eraTo": "1800",
    "tagset": "TDN-Core",
    "dataset": true,
    "public": true,
    "sourceName": "clariah-evaluation-18",
    "sourceURL": "https://dbnl.org",
    "version": "0.9",
    "description": "CLARIAH Evaluation set 1700-1800"
},
{
    "sourcePath": "source-data/clariah-evaluation-19",
    "trainingPath": "training-data/clariah-evaluation-19",
    "columns": [
        "token",
        "pos",
        "lemma"
    ],
    "name": "clariah-evaluation-19",
    "eraFrom": "1800",
    "eraTo": "1900",
    "tagset": "TDN-Core",
    "dataset": true,
    "public": true,
    "sourceName": "clariah-evaluation-19",
    "sourceURL": "https://dbnl.org",
    "version": "0.9",
    "description": "CLARIAH Evaluation set 1800-1900"
},
{
    "sourcePath": "source-data/clvn",
    "trainingPath": "training-data/clvn",
    "columns": [
        "token",
        "pos",
        "lemma"
    ],
    "name": "clvn",
    "eraFrom": "1500",
    "eraTo": "1700",
    "tagset": "TDN-Core",
    "dataset": true,
    "public": true,
    "sourceName": "clvn",
    "sourceURL": "https://ivdnt.org/actueel/nieuws/digitaaljaar-2024-databanken-van-nicoline/",
    "version": "0.9",
    "description": "CLVN Selection"
},
{
    "sourcePath": "source-data/couranten",
    "trainingPath": "training-data/couranten",
    "columns": [
        "token",
        "pos",
        "lemma"
    ],
    "name": "couranten",
    "eraFrom": "1600",
    "eraTo": "1700",
    "tagset": "TDN-Core",
    "dataset": true,
    "public": true,
    "sourceName": "couranten",
    "sourceURL": "https://couranten.ivdnt.org/",
    "version": "0.9",
    "description": "Couranten Corpus selection"
},
{
    "sourcePath": "source-data/dictionary-quotations-14",
    "trainingPath": "training-data/dictionary-quotations-14",
    "columns": [
        "token",
        "pos",
        "lemma"
    ],
    "name": "dictionary-quotations-14",
    "eraFrom": "1300",
    "eraTo": "1400",
    "tagset": "TDN-Core",
    "dataset": true,
    "public": true,
    "sourceName": "dictionary-quotations-14",
    "sourceURL": "https://gtb.ivdnt.org/",
    "version": "0.9",
    "description": "Historical Dictionary Quotations, 1300-1400"
},
{
    "sourcePath": "source-data/dictionary-quotations-15",
    "trainingPath": "training-data/dictionary-quotations-15",
    "columns": [
        "token",
        "pos",
        "lemma"
    ],
    "name": "dictionary-quotations-15",
    "eraFrom": "1400",
    "eraTo": "1500",
    "tagset": "TDN-Core",
    "dataset": true,
    "public": true,
    "sourceName": "dictionary-quotations-15",
    "sourceURL": "https://gtb.ivdnt.org/",
    "version": "0.9",
    "description": "Historical Dictionary Quotations, 1400-1500"
},
{
    "sourcePath": "source-data/dictionary-quotations-16",
    "trainingPath": "training-data/dictionary-quotations-16",
    "columns": [
        "token",
        "pos",
        "lemma"
    ],
    "name": "dictionary-quotations-16",
    "eraFrom": "1500",
    "eraTo": "1600",
    "tagset": "TDN-Core",
    "dataset": true,
    "public": true,
    "sourceName": "dictionary-quotations-16",
    "sourceURL": "https://gtb.ivdnt.org/",
    "version": "0.9",
    "description": "Historical Dictionary Quotations, 1500-1600 "
},
{
    "sourcePath": "source-data/dictionary-quotations-17",
    "trainingPath": "training-data/dictionary-quotations-17",
    "columns": [
        "token",
        "pos",
        "lemma"
    ],
    "name": "dictionary-quotations-17",
    "eraFrom": "1600",
    "eraTo": "1700",
    "tagset": "TDN-Core",
    "dataset": true,
    "public": true,
    "sourceName": "dictionary-quotations-17",
    "sourceURL": "https://gtb.ivdnt.org/",
    "version": "0.9",
    "description": "Historical Dictionary Quotations, 1600-1700 "
},
{
    "sourcePath": "source-data/dictionary-quotations-18",
    "trainingPath": "training-data/dictionary-quotations-18",
    "columns": [
        "token",
        "pos",
        "lemma"
    ],
    "name": "dictionary-quotations-18",
    "eraFrom": "1700",
    "eraTo": "1800",
    "tagset": "TDN-Core",
    "dataset": true,
    "public": true,
    "sourceName": "dictionary-quotations-18",
    "sourceURL": "https://gtb.ivdnt.org/",
    "version": "0.9",
    "description": "Historical Dictionary Quotations, 1700-1800"
},
{
    "sourcePath": "source-data/dictionary-quotations-19",
    "trainingPath": "training-data/dictionary-quotations-19",
    "columns": [
        "token",
        "pos",
        "lemma"
    ],
    "name": "dictionary-quotations-19",
    "eraFrom": "1800",
    "eraTo": "1900",
    "tagset": "TDN-Core",
    "dataset": true,
    "public": true,
    "sourceName": "dictionary-quotations-19",
    "sourceURL": "https://gtb.ivdnt.org/",
    "version": "0.9",
    "description": "Historical Dictionary Quotations, 1800-1900"
},
{
    "sourcePath": "source-data/letters-as-loot",
    "trainingPath": "training-data/letters-as-loot",
    "columns": [
        "token",
        "pos",
        "lemma"
    ],
    "name": "letters-as-loot",
    "eraFrom": "1600",
    "eraTo": "1800",
    "tagset": "TDN-Core",
    "dataset": true,
    "public": true,
    "sourceName": "letters-as-loot",
    "sourceURL": "https://brievenalsbuit.ivdnt.org/",
    "version": "0.9",
    "description": "Letters as Loot selection"
}]
